jaymap/__init__.py
jaymap/__version__.py
jaymap-0.dist-info/LICENSE
jaymap-0.dist-info/WHEEL
jaymap-0.dist-info/METADATA
jaymap-0.dist-info/RECORD
