Metadata-Version: 2.1
Name: jaymap
Version: 0
Summary: JMAP client for asyncio
Home-page: https://github.com/jreese/jaymap
License: UNKNOWN
Author: John Reese
Author-email: john@noswap.com
Requires-Python: >=3.7
Classifier: Framework :: AsyncIO
Classifier: Intended Audience :: Developers
Classifier: License :: OSI Approved :: MIT License
Classifier: Topic :: Software Development :: Libraries
